img/generate_spider_benchmark_plots.py
schema_search/__init__.py
schema_search/graph_builder.py
schema_search/mcp_server.py
schema_search/metrics.py
schema_search/schema_search.py
schema_search/types.py
schema_search/chunkers/__init__.py
schema_search/chunkers/base.py
schema_search/chunkers/factory.py
schema_search/chunkers/llm.py
schema_search/chunkers/markdown.py
schema_search/embedding_cache/__init__.py
schema_search/embedding_cache/base.py
schema_search/embedding_cache/bm25.py
schema_search/embedding_cache/factory.py
schema_search/embedding_cache/inmemory.py
schema_search/extractors/__init__.py
schema_search/extractors/base.py
schema_search/extractors/databricks.py
schema_search/extractors/factory.py
schema_search/extractors/sqlalchemy.py
schema_search/rankers/__init__.py
schema_search/rankers/base.py
schema_search/rankers/cross_encoder.py
schema_search/rankers/factory.py
schema_search/renderers/__init__.py
schema_search/renderers/base.py
schema_search/renderers/factory.py
schema_search/renderers/json.py
schema_search/renderers/markdown.py
schema_search/search/__init__.py
schema_search/search/base.py
schema_search/search/bm25.py
schema_search/search/factory.py
schema_search/search/fuzzy.py
schema_search/search/hybrid.py
schema_search/search/semantic.py
schema_search/utils/__init__.py
schema_search/utils/cache.py
schema_search/utils/config.py
schema_search/utils/utils.py
schema_search-3.0.0.dist-info/licenses/LICENSE
tests/__init__.py
tests/test_databricks.py
tests/test_db_raw.py
tests/test_integration.py
tests/test_llm_sql_generation.py
tests/test_spider_eval.py
schema_search-3.0.0.dist-info/METADATA
schema_search-3.0.0.dist-info/WHEEL
schema_search-3.0.0.dist-info/entry_points.txt
schema_search-3.0.0.dist-info/top_level.txt
schema_search-3.0.0.dist-info/RECORD
