Metadata-Version: 2.4
Name: schema-search
Version: 3.0.0
Summary: Natural language database schema search with graph-aware semantic retrieval
Author: Adib Hasan
License-Expression: MIT
Project-URL: Homepage, https://adibhasan.com/blog/schema-search/
Classifier: Development Status :: 3 - Alpha
Classifier: Intended Audience :: Developers
Classifier: Programming Language :: Python :: 3
Classifier: Programming Language :: Python :: 3.10
Classifier: Programming Language :: Python :: 3.11
Requires-Python: >=3.10
License-File: LICENSE
Requires-Dist: sqlalchemy>=1.4.0
Requires-Dist: networkx>=2.8.0
Requires-Dist: bm25s>=0.2.0
Requires-Dist: numpy>=1.21.0
Requires-Dist: pyyaml>=6.0
Requires-Dist: tqdm>=4.65.0
Requires-Dist: rapidfuzz>=3.0.0
Provides-Extra: semantic
Requires-Dist: sentence-transformers>=2.2.0; extra == "semantic"
Provides-Extra: llm
Requires-Dist: openai>=1.0.0; extra == "llm"
Provides-Extra: mcp
Requires-Dist: fastmcp>=2.0.0; extra == "mcp"
Provides-Extra: test
Requires-Dist: pytest>=7.0.0; extra == "test"
Requires-Dist: python-dotenv>=1.0.0; extra == "test"
Requires-Dist: psutil>=5.9.0; extra == "test"
Requires-Dist: datasets>=2.0.0; extra == "test"
Provides-Extra: postgres
Requires-Dist: psycopg2-binary>=2.9.0; extra == "postgres"
Provides-Extra: mysql
Requires-Dist: pymysql>=1.0.0; extra == "mysql"
Provides-Extra: snowflake
Requires-Dist: snowflake-sqlalchemy>=1.4.0; extra == "snowflake"
Requires-Dist: snowflake-connector-python>=3.0.0; extra == "snowflake"
Provides-Extra: bigquery
Requires-Dist: sqlalchemy-bigquery>=1.6.0; extra == "bigquery"
Provides-Extra: databricks
Requires-Dist: databricks-sqlalchemy>=2.0.0; extra == "databricks"
Dynamic: license-file
